{
    "type": "FeatureCollection",
    "name": "Orion_Christchurch_2025 - Imagery_Centres",
    "crs": {
        "type": "name",
        "properties": {
            "name": "urn:ogc:def:crs:OGC:1.3:CRS84"
        }
    },
    "features": [
        {
            "type": "Feature",
            "properties": {
                "Project": "PGRM3232",
                "Company_Name": "Orion",
                "SN_No": "SN14390",
                "Survey_Typ": "Imagery",
                "Proj_Name": "Orion Christchurch",
                "OrthoGSD_m": 0.20,
                "Area": 4824.1370404066001,
                "Percentage_Coverage": 100.0
            },
            "geometry": {
                "type": "Point",
                "coordinates": [
                    172.292630646530853,
                    -43.581586807335697
                ]
            }
        }
    ]
}